stalse_functions/__init__.py
stalse_functions/stalse_functions.py
stalse_functions-0.1.dist-info/METADATA
stalse_functions-0.1.dist-info/WHEEL
stalse_functions-0.1.dist-info/top_level.txt
stalse_functions-0.1.dist-info/RECORD
