Metadata-Version: 2.1
Name: stalse-functions
Version: 0.1
Summary: UNKNOWN
Home-page: UNKNOWN
Author: UNKNOWN
Author-email: UNKNOWN
License: UNKNOWN
Platform: UNKNOWN
Requires-Dist: pandas-gbq
Requires-Dist: pandas
Requires-Dist: flask
Requires-Dist: google-cloud-storage
Requires-Dist: google-cloud-secret-manager
